zlx/__init__.py
zlx/bin.py
zlx/build_number.py
zlx/cmd_line.py
zlx/int.py
zlx/io.py
zlx/msf7.py
zlx/mth.py
zlx/pdb.py
zlx/pe.py
zlx/record.py
zlx/utils.py
zlx/windump.py
zlx/wire.py
zlx-0.0.15.dist-info/LICENSE
zlx-0.0.15.dist-info/METADATA
zlx-0.0.15.dist-info/WHEEL
zlx-0.0.15.dist-info/entry_points.txt
zlx-0.0.15.dist-info/top_level.txt
zlx-0.0.15.dist-info/RECORD
