Metadata-Version: 2.1
Name: zlx
Version: 0.0.15
Summary: Zalmoxis - module for text and binary manipulation
Home-page: https://gitlab.com/icostin/zlx-py
Author: Costin Ionescu
Author-email: costin.ionescu@gmail.com
License: MIT
Platform: UNKNOWN
Classifier: Programming Language :: Python :: 3
Classifier: License :: OSI Approved :: MIT License
Classifier: Operating System :: OS Independent
